README.md
setup.py
Zeus_CI.egg-info/PKG-INFO
Zeus_CI.egg-info/SOURCES.txt
Zeus_CI.egg-info/dependency_links.txt
Zeus_CI.egg-info/entry_points.txt
Zeus_CI.egg-info/requires.txt
Zeus_CI.egg-info/top_level.txt
zeus_ci/__init__.py
zeus_ci/build_coordinator/__init__.py
zeus_ci/cli/__init__.py
zeus_ci/listeners/__init__.py
zeus_ci/persistence/__init__.py
zeus_ci/runner/__init__.py
zeus_ci/scm_reporter/__init__.py