Metadata-Version: 1.2
Name: Zeus-CI
Version: 0.0.3.post1556521419
Summary: python CI server that tries to not suck
Home-page: https://github.com/chestm007/lcircle
Author: Max Chesterfield
Author-email: chestm007@hotmail.com
Maintainer: Max Chesterfield
Maintainer-email: chestm007@hotmail.com
License: GPL-2.0
Platform: UNKNOWN
